MANIFEST.in
MIT-LICENSE
README.rst
setup.cfg
setup.py
clplot/__init__.py
clplot/main.py
clplot.egg-info/PKG-INFO
clplot.egg-info/SOURCES.txt
clplot.egg-info/dependency_links.txt
clplot.egg-info/entry_points.txt
clplot.egg-info/top_level.txt