Metadata-Version: 1.1
Name: clplot
Version: 0.2a0
Summary: clplot is a command line utility to create plots and pages of plots from csv-like files.
Home-page: https://github.com/breisfeld/clplot
Author: Brad Reisfeld
Author-email: brad.reisfeld@gmail.com
License: UNKNOWN
Keywords: plotting,matplotlib
Platform: UNKNOWN
Classifier: Programming Language :: Python :: 2
Classifier: Development Status :: 3 - Alpha
Classifier: Operating System :: OS Independent
Classifier: Intended Audience :: End Users/Desktop
Classifier: License :: OSI Approved :: MIT License
Classifier: Topic :: Utilities
Classifier: Topic :: Scientific/Engineering
